src/scu.v
module scu (
    input  wire [0:0] clk, rstn,
    input  wire [0:0] sel_m1, sel_m2, endtrans,
    output reg  [1:0] mas_sel
);
    //States
    localparam START  = 2'b00;
    localparam GRANT1 = 2'b01;
    localparam GRANT2 = 2'b10;
    localparam NEXT   = 2'b11;
    //Internal signals
    reg [1:0] state, next_state;
    reg [0:0] next_gr;

    always@(posedge clk or negedge rstn) begin
        if(!rstn)
            state <= START;
        else
            state <= next_state; 
    end

    always@(*) begin
        case(state)
            START:  begin
                if (sel_m1 == 1'b1)
                    next_state = GRANT1;
                else if ((sel_m1 == 1'b0 && sel_m2 == 1'b1))
                    next_state = GRANT2;
                else
                    next_state = state;
            end
            GRANT1: begin
                if (endtrans == 1'b1)
                    next_state = NEXT;
                else
                    next_state = state;
            end
            GRANT2: begin
                if (endtrans == 1'b1)
                    next_state = NEXT;
                else
                    next_state = state;
            end
            NEXT:   begin
                if ((sel_m1 == 1'b1 && sel_m2 == 1'b0) || (sel_m1 == 1'b1 && sel_m2 == 1'b1 && next_gr == 1'b0))
                    next_state = GRANT1;
                else if ((sel_m1 == 1'b0 && sel_m2 == 1'b1) || (sel_m1 == 1'b1 && sel_m2 == 1'b1 && next_gr == 1'b1))
                    next_state = GRANT2;
                else
                    next_state = state;
            end
            default: next_state = START;
        endcase
    end

    always@(*) begin
        case(state)
            START:  begin
                mas_sel = 2'b00;
                next_gr = 1'b0;
            end
            GRANT1: begin
                mas_sel = 2'b01;
                next_gr = 1'b1;
            end
            GRANT2: begin
                mas_sel = 2'b10;
                next_gr = 1'b0;
            end
            NEXT: mas_sel = 2'b00;
            default: begin
                mas_sel = 2'b10;
                next_gr = 1'b0;
            end
        endcase
    end

endmodule

tb/scu_tb.sv
`timescale 1ns/1ps
module scu_tb();
    logic [0:0] sel_m1, sel_m2, endtrans;
    logic [1:0] mas_sel;
    logic i_clk, i_rstn;

    scu scu_inst (
        .clk          (i_clk),
        .rstn         (i_rstn),
        .sel_m1       (sel_m1),
        .sel_m2       (sel_m2),
        .endtrans     (endtrans),
        .mas_sel      (mas_sel)
    );

    // Clock gen
    initial begin
        i_clk = 0;
        forever #5 i_clk = ~i_clk;
    end

    initial begin
        i_rstn = 0;
        #10;
        i_rstn = 1;
    end

    // Wave dump
    initial begin
        $dumpfile("scu_tb.vcd");
        $dumpvars(0,scu_tb);      
    end

    int cnt = 1;
    initial begin
    // Initialize signals
        sel_m1 = 0;
        sel_m2 = 0;
        endtrans = 0;

        repeat (100) begin
            {sel_m1, sel_m2, endtrans} = $random % 8; 
            if (cnt != 0) #7.5;
            else #10;
            //#10; // Wait for FSM response
            $display("Time=%0.1f | sel_m1=%b | sel_m2=%b | endtrans=%b | mas_sel=%b  | state=%b", 
                     $realtime, sel_m1, sel_m2, endtrans, mas_sel, scu_inst.state);
            cnt = 0;
        end

        #10 $finish;
    end

endmodule

sim/scu_tb.vcd
$date
	Fri Mar  7 15:44:56 2025
$end
$version
	Icarus Verilog
$end
$timescale
	1ps
$end
$scope module scu_tb $end
$var wire 2 ! mas_sel [1:0] $end
$var reg 1 " endtrans $end
$var reg 1 # i_clk $end
$var reg 1 $ i_rstn $end
$var reg 1 % sel_m1 $end
$var reg 1 & sel_m2 $end
$var integer 32 ' cnt [31:0] $end
$scope module scu_inst $end
$var wire 1 # clk $end
$var wire 1 " endtrans $end
$var wire 1 $ rstn $end
$var wire 1 % sel_m1 $end
$var wire 1 & sel_m2 $end
$var parameter 2 ( GRANT1 $end
$var parameter 2 ) GRANT2 $end
$var parameter 2 * NEXT $end
$var parameter 2 + START $end
$var reg 2 , mas_sel [1:0] $end
$var reg 1 - next_gr $end
$var reg 2 . next_state [1:0] $end
$var reg 2 / state [1:0] $end
$upscope $end
$upscope $end
$enddefinitions $end
$comment Show the parameter values. $end
$dumpall
b0 +
b11 *
b10 )
b1 (
$end
#0
$dumpvars
b0 /
b1 .
0-
b0 ,
b1 '
0&
1%
0$
0#
0"
b0 !
$end
#5000
1#
#7500
b0 .
0%
1"
b0 '
#10000
0#
1$
#15000
1#
#20000
0#
#25000
1#
#27500
b10 .
1&
#30000
0#
#35000
b10 !
b10 ,
b11 .
b10 /
1#
#37500
1%
0&
#40000
0#
#45000
b0 !
b0 ,
b1 .
b11 /
1#
#50000
0#
#55000
1-
b1 !
b1 ,
b11 .
b1 /
1#
#60000
0#
#65000
b0 !
b0 ,
b1 .
b11 /
1#
#67500
b10 .
0%
1&
0"
#70000
0#
#75000
0-
b10 !
b10 ,
b10 /
1#
#77500
b11 .
0&
1"
#80000
0#
#85000
b0 !
b0 ,
b11 /
1#
#87500
b1 .
1%
#90000
0#
#95000
1-
b1 !
b1 ,
b11 .
b1 /
1#
#97500
b1 .
1&
0"
#100000
0#
#105000
1#
#107500
b11 .
0&
1"
#110000
0#
#115000
b0 !
b0 ,
b1 .
b11 /
1#
#120000
0#
#125000
b1 !
b1 ,
b11 .
b1 /
1#
#127500
b1 .
0"
#130000
0#
#135000
1#
#137500
b11 .
0%
1"
#140000
0#
#145000
b0 !
b0 ,
b11 /
1#
#147500
b10 .
1%
1&
0"
#150000
0#
#155000
0-
b10 !
b10 ,
b10 /
1#
#157500
b11 .
0&
1"
#160000
0#
#165000
b0 !
b0 ,
b1 .
b11 /
1#
#167500
b10 .
0%
1&
0"
#170000
0#
#175000
b10 !
b10 ,
b10 /
1#
#177500
b11 .
1%
0&
1"
#180000
0#
#185000
b0 !
b0 ,
b1 .
b11 /
1#
#187500
1&
#190000
0#
#195000
1-
b1 !
b1 ,
b11 .
b1 /
1#
#197500
b1 .
0%
0"
#200000
0#
#205000
1#
#207500
b11 .
1%
1"
#210000
0#
#215000
b0 !
b0 ,
b10 .
b11 /
1#
#217500
0%
0"
#220000
0#
#225000
0-
b10 !
b10 ,
b10 /
1#
#227500
1%
#230000
0#
#235000
1#
#237500
0%
0&
#240000
0#
#245000
1#
#247500
b11 .
1%
1"
#250000
0#
#255000
b0 !
b0 ,
b1 .
b11 /
1#
#257500
0"
#260000
0#
#265000
1-
b1 !
b1 ,
b1 /
1#
#267500
b11 .
1"
#270000
0#
#275000
b0 !
b0 ,
b1 .
b11 /
1#
#280000
0#
#285000
b1 !
b1 ,
b11 .
b1 /
1#
#290000
0#
#295000
b0 !
b0 ,
b1 .
b11 /
1#
#297500
b10 .
0%
1&
#300000
0#
#305000
0-
b10 !
b10 ,
b11 .
b10 /
1#
#307500
b10 .
0"
#310000
0#
#315000
1#
#317500
0&
#320000
0#
#325000
1#
#330000
0#
#335000
1#
#337500
1&
#340000
0#
#345000
1#
#347500
b11 .
1%
0&
1"
#350000
0#
#355000
b0 !
b0 ,
b1 .
b11 /
1#
#357500
1&
0"
#360000
0#
#365000
1-
b1 !
b1 ,
b1 /
1#
#367500
b11 .
0%
1"
#370000
0#
#375000
b0 !
b0 ,
b10 .
b11 /
1#
#377500
b1 .
1%
0&
#380000
0#
#385000
b1 !
b1 ,
b11 .
b1 /
1#
#387500
0%
1&
#390000
0#
#395000
b0 !
b0 ,
b10 .
b11 /
1#
#400000
0#
#405000
0-
b10 !
b10 ,
b11 .
b10 /
1#
#407500
1%
0&
#410000
0#
#415000
b0 !
b0 ,
b1 .
b11 /
1#
#417500
b10 .
0%
1&
0"
#420000
0#
#425000
b10 !
b10 ,
b10 /
1#
#427500
1%
#430000
0#
#435000
1#
#437500
b11 .
0&
1"
#440000
0#
#445000
b0 !
b0 ,
b1 .
b11 /
1#
#447500
1&
#450000
0#
#455000
1-
b1 !
b1 ,
b11 .
b1 /
1#
#457500
0%
#460000
0#
#465000
b0 !
b0 ,
b10 .
b11 /
1#
#467500
0"
#470000
0#
#475000
0-
b10 !
b10 ,
b10 /
1#
#480000
0#
#485000
1#
#487500
1%
0&
#490000
0#
#495000
1#
#497500
0%
1&
#500000
0#
#505000
1#
#510000
0#
#515000
1#
#517500
b11 .
0&
1"
#520000
0#
#525000
b0 !
b0 ,
b11 /
1#
#527500
0"
#530000
0#
#535000
1#
#540000
0#
#545000
1#
#547500
1"
#550000
0#
#555000
1#
#557500
b10 .
1&
#560000
0#
#565000
b10 !
b10 ,
b11 .
b10 /
1#
#567500
b10 .
1%
0"
#570000
0#
#575000
1#
#580000
0#
#585000
1#
#590000
0#
#595000
1#
#597500
0&
#600000
0#
#605000
1#
#607500
0%
1&
#610000
0#
#615000
1#
#617500
b11 .
1"
#620000
0#
#625000
b0 !
b0 ,
b10 .
b11 /
1#
#627500
b11 .
0&
#630000
0#
#635000
1#
#637500
b1 .
1%
#640000
0#
#645000
1-
b1 !
b1 ,
b11 .
b1 /
1#
#647500
1&
#650000
0#
#655000
b0 !
b0 ,
b10 .
b11 /
1#
#657500
0%
#660000
0#
#665000
0-
b10 !
b10 ,
b11 .
b10 /
1#
#667500
b10 .
0"
#670000
0#
#675000
1#
#677500
1%
#680000
0#
#685000
1#
#687500
b11 .
0&
1"
#690000
0#
#695000
b0 !
b0 ,
b1 .
b11 /
1#
#697500
b11 .
0%
#700000
0#
#705000
1#
#710000
0#
#715000
1#
#717500
b10 .
1&
0"
#720000
0#
#725000
b10 !
b10 ,
b10 /
1#
#727500
1%
0&
#730000
0#
#735000
1#
#737500
b11 .
1&
1"
#740000
0#
#745000
b0 !
b0 ,
b1 .
b11 /
1#
#750000
0#
#755000
1-
b1 !
b1 ,
b11 .
b1 /
1#
#757500
b1 .
0%
0&
0"
#760000
0#
#765000
1#
#767500
b11 .
1%
1&
1"
#770000
0#
#775000
b0 !
b0 ,
b10 .
b11 /
1#
#780000
0#
#785000
0-
b10 !
b10 ,
b11 .
b10 /
1#
#787500
b10 .
0&
0"
#790000
0#
#795000
1#
#797500
b11 .
0%
1&
1"
#800000
0#
#805000
b0 !
b0 ,
b10 .
b11 /
1#
#807500
b11 .
0&
#810000
0#
#815000
1#
#820000
0#
#825000
1#
#827500
0"
#830000
0#
#835000
1#
#837500
b1 .
1%
1&
1"
#840000
0#
#845000
1-
b1 !
b1 ,
b11 .
b1 /
1#
#847500
0%
0&
#850000
0#
#855000
b0 !
b0 ,
b11 /
1#
#857500
b10 .
1%
1&
0"
#860000
0#
#865000
0-
b10 !
b10 ,
b10 /
1#
#867500
0&
#870000
0#
#875000
1#
#877500
0%
1&
#880000
0#
#885000
1#
#887500
0&
#890000
0#
#895000
1#
#897500
b11 .
1%
1&
1"
#900000
0#
#905000
b0 !
b0 ,
b1 .
b11 /
1#
#907500
0&
#910000
0#
#915000
1-
b1 !
b1 ,
b11 .
b1 /
1#
#917500
b1 .
0%
1&
0"
#920000
0#
#925000
1#
#927500
1%
#930000
0#
#935000
1#
#937500
b11 .
0&
1"
#940000
0#
#945000
b0 !
b0 ,
b1 .
b11 /
1#
#947500
b11 .
0%
#950000
0#
#955000
1#
#957500
b10 .
1%
1&
#960000
0#
#965000
0-
b10 !
b10 ,
b11 .
b10 /
1#
#967500
0%
#970000
0#
#975000
b0 !
b0 ,
b10 .
b11 /
1#
#977500
b1 .
1%
0&
#980000
0#
#985000
1-
b1 !
b1 ,
b11 .
b1 /
1#
#987500
b1 .
0%
0"
